mkdocs_pygments-0.1.0.dist-info/METADATA
mkdocs_pygments-0.1.0.dist-info/WHEEL
mkdocs_pygments-0.1.0.dist-info/entry_points.txt
mkdocs_pygments-0.1.0.dist-info/licenses/LICENSE
mkdocs_pygments/__init__.py
mkdocs_pygments/_internal/__init__.py
mkdocs_pygments/_internal/debug.py
mkdocs_pygments/_internal/plugin.py
mkdocs_pygments/py.typed
mkdocs_pygments-0.1.0.dist-info/RECORD
